market_maker/__init__.py
market_maker/_settings_base.py
market_maker/bitmex.py
market_maker/market_maker.py
market_maker/market_maker_runner.py
market_maker/quant_base_strategy.py
market_maker/quant_position_manager_strategy.py
market_maker/quant_position_swinger_strategy.py
market_maker/settings.py
market_maker/auth/APIKeyAuth.py
market_maker/auth/APIKeyAuthWithExpires.py
market_maker/auth/AccessTokenAuth.py
market_maker/auth/__init__.py
market_maker/utils/__init__.py
market_maker/utils/constants.py
market_maker/utils/dotdict.py
market_maker/utils/errors.py
market_maker/utils/log.py
market_maker/utils/math.py
market_maker/ws/__init__.py
market_maker/ws/ws_thread.py
quant_trading_bitmex_market_maker-2.8.0.dist-info/LICENSE
quant_trading_bitmex_market_maker-2.8.0.dist-info/METADATA
quant_trading_bitmex_market_maker-2.8.0.dist-info/WHEEL
quant_trading_bitmex_market_maker-2.8.0.dist-info/entry_points.txt
quant_trading_bitmex_market_maker-2.8.0.dist-info/top_level.txt
quant_trading_bitmex_market_maker-2.8.0.dist-info/RECORD
