Metadata-Version: 2.1
Name: quant-trading-bitmex-market-maker
Version: 2.8.0
Summary: Market making bot for BitMEX API
Home-page: https://github.com/Quant-Network/sample-market-maker
Author: Quant-trading.Network
Author-email: support@quant-trading.network
License: UNKNOWN
Download-URL: https://github.com/Quant-Network/sample-market-maker/archive/v2.8.tar.gz
Keywords: Market making bot,BitMEX Market making bot,algorithmic trading,trading,bitcoin
Platform: UNKNOWN
Requires-Dist: requests
Requires-Dist: websocket-client
Requires-Dist: future
Requires-Dist: quant-trading-api
